ComicThief/__init__.py
ComicThief/cache.py
ComicThief/config.py
ComicThief/creator.py
ComicThief/ct.py
ComicThief/default.ini
ComicThief/extractor.py
ComicThief/fetcher.py
ComicThief/main.py
ComicThief/test.py
ComicThief-0.2.1.dist-info/DESCRIPTION.rst
ComicThief-0.2.1.dist-info/METADATA
ComicThief-0.2.1.dist-info/RECORD
ComicThief-0.2.1.dist-info/WHEEL
ComicThief-0.2.1.dist-info/metadata.json
ComicThief-0.2.1.dist-info/top_level.txt
